redmask/__init__.py
redmask/__main__.py
redmask/gpl.py
redmask/redmask.py
redmask-1.1.0.dist-info/LICENSE
redmask-1.1.0.dist-info/METADATA
redmask-1.1.0.dist-info/WHEEL
redmask-1.1.0.dist-info/entry_points.txt
redmask-1.1.0.dist-info/top_level.txt
redmask-1.1.0.dist-info/RECORD
