Metadata-Version: 2.1
Name: redmask
Version: 1.1.0
Summary: A simple tool to create palette swap mask
Home-page: https://github.com/williamd1k0/redmask
Author: William Tumeo
Author-email: pypi@tumeo.space
License: UNKNOWN
Download-URL: https://github.com/williamd1k0/redmask/archive/v1.1.0.tar.gz
Keywords: palette,gimp,krita,shaders
Platform: UNKNOWN
Classifier: Topic :: Utilities
Classifier: Topic :: Multimedia :: Graphics
Classifier: Environment :: Console
Classifier: Environment :: Win32 (MS Windows)
Classifier: Environment :: MacOS X
Classifier: Operating System :: POSIX :: Linux
Classifier: Operating System :: MacOS
Classifier: Operating System :: Microsoft
Classifier: Operating System :: Microsoft :: Windows :: Windows 7
Classifier: Operating System :: Microsoft :: Windows :: Windows XP
Classifier: Operating System :: Microsoft :: Windows :: Windows Vista
Classifier: Intended Audience :: End Users/Desktop
Classifier: Intended Audience :: Developers
Classifier: Programming Language :: Python
Classifier: Programming Language :: Python :: 3
Classifier: Programming Language :: Python :: 3.5
Classifier: Programming Language :: Python :: 3.6
Classifier: Programming Language :: Python :: 3.7
Classifier: Programming Language :: Python :: 3.8
Classifier: Programming Language :: Python :: 3 :: Only
Classifier: Development Status :: 5 - Production/Stable
Classifier: License :: OSI Approved :: MIT License
Requires-Dist: pillow (>=5.0.0)
